{
  "type": "materials",
  "path": "Dämmstoffe / Wärmedämmverbundsystem / Wärmedämmverbundsystem",
  "items": [
    {
      "ID": "2c031186-a7a9-43c2-abe6-1bb0dad15933",
      "Name": "ETICS gluing and coating mineral decor plaster",
      "Conformity": "'EN 15804+A2 (EF 3.1)'",
      "Laenderkennung": "DE",
      "Declaration owner": "Sphera Solutions GmbH",
      "Bezugsgroesse": "1",
      "Reference": "qm",
      "Flaechengewicht (kg/m2)": "17.4",
      "GWPtotal (A1-A3)": "7.7876367",
      "GWPtotal (C2)": "0.0741085",
      "GWPtotal (C4)": "0.522134",
      "GWPbiogenic": "0.0145417",
      "GWPfossil": "8.3455187",
      "GWPtotal": "8.3838793"
    },
    {
      "ID": "7e8801e0-c0e4-4995-bf8a-883181f6aa20",
      "Name": "ETICS gluing and coating mineral lightweight plaster",
      "Conformity": "'EN 15804+A2 (EF 3.1)'",
      "Laenderkennung": "DE",
      "Declaration owner": "Sphera Solutions GmbH",
      "Bezugsgroesse": "1",
      "Reference": "qm",
      "Flaechengewicht (kg/m2)": "11.4",
      "GWPtotal (A1-A3)": "4.9757308",
      "GWPtotal (C2)": "0.048548",
      "GWPtotal (C4)": "0.3437009",
      "GWPbiogenic": "0.0070957",
      "GWPfossil": "5.3524439",
      "GWPtotal": "5.3679798"
    },
    {
      "ID": "278ba020-5da0-4bfe-aa3c-477e02646244",
      "Name": "ETICS gluing and coating scratched plaster",
      "Conformity": "'EN 15804+A2 (EF 3.1)'",
      "Laenderkennung": "DE",
      "Declaration owner": "Sphera Solutions GmbH",
      "Bezugsgroesse": "1",
      "Reference": "qm",
      "Flaechengewicht (kg/m2)": "35.18",
      "GWPtotal (A1-A3)": "10.3382844",
      "GWPtotal (C2)": "0.149853",
      "GWPtotal (C4)": "1.0145035",
      "GWPbiogenic": "0.0143916",
      "GWPfossil": "11.4663513",
      "GWPtotal": "11.5026408"
    },
    {
      "ID": "b4cfc1a1-d1dc-413f-ab48-d6d52e498837",
      "Name": "ETICS gluing and coating silcate dispersion plaster",
      "Conformity": "'EN 15804+A2 (EF 3.1)'",
      "Laenderkennung": "DE",
      "Declaration owner": "Sphera Solutions GmbH",
      "Bezugsgroesse": "1",
      "Reference": "qm",
      "Flaechengewicht (kg/m2)": "12.3",
      "GWPtotal (A1-A3)": "5.741689",
      "GWPtotal (C2)": "0.0531489",
      "GWPtotal (C3)": "0.0",
      "GWPtotal (C4)": "0.2072875",
      "GWPbiogenic": "-0.0749863",
      "GWPfossil": "6.0654935",
      "GWPtotal": "6.0021254"
    },
    {
      "ID": "ba9c150e-4334-4bdf-ba93-337ea848c7ea",
      "Name": "ETICS gluing and coating silicate dispersion plaster",
      "Conformity": "'EN 15804+A2 (EF 3.1)'",
      "Laenderkennung": "DE",
      "Declaration owner": "Sphera Solutions GmbH",
      "Bezugsgroesse": "1",
      "Reference": "qm",
      "Flaechengewicht (kg/m2)": "12.48",
      "GWPtotal (A1-A3)": "5.741689",
      "GWPtotal (C2)": "0.0531489",
      "GWPtotal (C3)": "0.0",
      "GWPtotal (C4)": "0.2072875",
      "GWPbiogenic": "-0.0749863",
      "GWPfossil": "6.0654935",
      "GWPtotal": "6.0021254"
    },
    {
      "ID": "18dd486c-bf09-44a7-bdb4-3996e3bb854c",
      "Name": "ETICS gluing and coating synthetic resin plaster",
      "Conformity": "'EN 15804+A2 (EF 3.1)'",
      "Laenderkennung": "DE",
      "Declaration owner": "Sphera Solutions GmbH",
      "Bezugsgroesse": "1",
      "Reference": "qm",
      "Flaechengewicht (kg/m2)": "12.48",
      "GWPtotal (A1-A3)": "6.9588011",
      "GWPtotal (C2)": "0.0531489",
      "GWPtotal (C3)": "0.0",
      "GWPtotal (C4)": "0.2072875",
      "GWPbiogenic": "-0.0378657",
      "GWPfossil": "7.2447397",
      "GWPtotal": "7.2192376"
    },
    {
      "ID": "6d16dafc-0a4b-496a-9f3f-39c066bc0401",
      "Name": "External thermal insulation composite system EPS with rail fastening",
      "Conformity": "'EN 15804+A2 (EF 3.1)'",
      "Laenderkennung": "DE",
      "Declaration owner": "Sphera Solutions GmbH",
      "Bezugsgroesse": "1",
      "Reference": "qm",
      "Flaechengewicht (kg/m2)": "14.848",
      "GWPtotal (A1-A3)": "26.0930332",
      "GWPtotal (C2)": "0.0687909",
      "GWPtotal (C4)": "0.3348547",
      "GWPbiogenic": "-0.987785",
      "GWPfossil": "27.4518782",
      "GWPtotal": "26.4966789"
    },
    {
      "ID": "b2b871e7-d328-4ae4-a5ef-460aebe1c763",
      "Name": "SN 40.01 - Modified flour",
      "Conformity": "'EN 15804+A2' / 'ISO 14025'",
      "Laenderkennung": "RER",
      "Declaration owner": "ceresan Erfurt GmbH",
      "Registrierungsnummer": "EPD-Kiwa-EE-169737-EN",
      "Bezugsgroesse": "1",
      "Reference": "kg",
      "Density (kg/m3)": "530.0",
      "GWPtotal (A1)": "-0.9928834",
      "GWPtotal (A2)": "0.0104625",
      "GWPtotal (A3)": "0.2528333",
      "GWPtotal (C1)": "0.0032793",
      "GWPtotal (C2)": "0.0199222",
      "GWPtotal (C3)": "1.5923054",
      "GWPtotal (C4)": "0.0478571",
      "GWPbiogenic": "0.396507",
      "GWPfossil": "0.9093875",
      "GWPtotal": "0.9337765"
    }
  ]
}