{
  "type": "materials",
  "path": "Mineralische Baustoffe / Steine und Elemente / Trockenestrich",
  "items": [
    {
      "ID": "f6878cee-a4bd-43da-a830-c64b975cb957",
      "Name": "DRY SCREED PLASTERBOARD / Tool",
      "Conformity": "'DIN EN 15804+A2' / 'ISO 14025'",
      "Laenderkennung": "DE",
      "Declaration owner": "Bundesverband der Gipsindustrie e.V.",
      "Registrierungsnummer": "EPD-BVG-20210341-IBE1-DE",
      "Bezugsgroesse": "1",
      "Reference": "qm",
      "Flaechengewicht (kg/m2)": "20.0",
      "Density (kg/m3)": "680.0",
      "Schichtdicke (m)": "0.025",
      "GWPtotal (A1-A3)": "1.806536",
      "GWPtotal (A4)": "0.229413",
      "GWPtotal (A5)": "0.0020224",
      "GWPtotal (C1)": "0.0",
      "GWPtotal (C2)": "0.1257402",
      "GWPtotal (C3)": "1.6263775",
      "GWPtotal (C4)": "0.0",
      "GWPbiogenic": "-0.8957866",
      "GWPfossil": "6.330341",
      "GWPtotal": "3.7900891"
    },
    {
      "ID": "be06a50c-9a4a-4af7-837d-abc46d0d3da9",
      "Name": "Dry Screed Fibreboard/Tool",
      "Conformity": "'DIN EN 15804+A2' / 'ISO 14025'",
      "Laenderkennung": "DE",
      "Declaration owner": "Bundesverband der Gipsindustrie e.V.",
      "Registrierungsnummer": "EPD-BVG-20220091-IAG1-DE",
      "Bezugsgroesse": "1",
      "Reference": "qm",
      "Flaechengewicht (kg/m2)": "24.0",
      "Schichtdicke (m)": "0.025",
      "GWPtotal (A1-A3)": "7.0264007",
      "GWPtotal (A4)": "0.2188043",
      "GWPtotal (A5)": "0.0010112",
      "GWPtotal (C1)": "0.0",
      "GWPtotal (C2)": "0.1508883",
      "GWPtotal (C3)": "3.9157958",
      "GWPtotal (C4)": "0.0",
      "GWPbiogenic": "-2.6138783",
      "GWPfossil": "17.9995056",
      "GWPtotal": "11.3129002"
    },
    {
      "ID": "94b1c5c8-659a-4585-b0a2-4a4ffc2a64f6",
      "Name": "Dry floor screed (gypsum fiber board, 25 mm)",
      "Conformity": "'EN 15804+A2 (EF 3.1)'",
      "Laenderkennung": "DE",
      "Declaration owner": "Sphera Solutions GmbH",
      "Bezugsgroesse": "1",
      "Reference": "qm",
      "Flaechengewicht (kg/m2)": "24.07",
      "GWPtotal (A1-A3)": "7.8247972",
      "GWPtotal (C2)": "0.1026682",
      "GWPtotal (C4)": "0.4004192",
      "GWPbiogenic": "0.0227043",
      "GWPfossil": "8.2964034",
      "GWPtotal": "8.3278846"
    },
    {
      "ID": "f4ef6362-85e1-4aac-b263-d954d1acbcd1",
      "Name": "Dry floor screed (gypsum plaster board, 25 mm)",
      "Conformity": "'EN 15804+A2 (EF 3.1)'",
      "Laenderkennung": "DE",
      "Declaration owner": "Sphera Solutions GmbH",
      "Bezugsgroesse": "1",
      "Reference": "qm",
      "Flaechengewicht (kg/m2)": "20.07",
      "GWPtotal (A1-A3)": "3.4576916",
      "GWPtotal (C2)": "0.0855",
      "GWPtotal (C4)": "1.5411461",
      "GWPbiogenic": "0.0150419",
      "GWPfossil": "5.0610438",
      "GWPtotal": "5.0843377"
    }
  ]
}