{
  "type": "materials",
  "path": "Dämmstoffe / Expandiertes Polystyrol (EPS) / EPS weiß",
  "items": [
    {
      "ID": "121c71e8-0f4c-4529-b72e-331198d15f0f",
      "Name": "2.2.01. EPS rigid foam insulation",
      "Conformity": "'EN 15804+A2 (EF 3.1)'",
      "Laenderkennung": "DE",
      "Declaration owner": "Sphera Solutions GmbH",
      "Bezugsgroesse": "1",
      "Reference": "m3",
      "Density (kg/m3)": "25.0",
      "GWPtotal (A1-A3)": "86.9290183",
      "GWPtotal (C2)": "0.1065023",
      "GWPtotal (C3)": "92.2861461",
      "GWPbiogenic": "0.4929676",
      "GWPfossil": "178.7866731",
      "GWPtotal": "179.3216667"
    },
    {
      "ID": "205b761d-e344-49c3-a3a9-bb1bfd59b916",
      "Name": "Expanded Polystyrene (EPS) Foam Insulation (density 15 kg/m³)",
      "Conformity": "'DIN EN 15804+A2' / 'ISO 14025'",
      "Laenderkennung": "DE",
      "Declaration owner": "Industrieverband Hartschaum e.V., IVH",
      "Registrierungsnummer": "EPD-IVH-20220129-CBG1-DE",
      "Bezugsgroesse": "1",
      "Reference": "m3",
      "Density (kg/m3)": "15.0",
      "GWPtotal (A1-A3)": "46.99",
      "GWPtotal (A5)": "0.591",
      "GWPtotal (C1)": "0.0",
      "GWPtotal (C2)": "0.0453",
      "GWPtotal (C3)": "50.4",
      "GWPtotal (C4)": "0.0",
      "GWPbiogenic": "0.245348",
      "GWPfossil": "97.7739",
      "GWPtotal": "98.0263"
    },
    {
      "ID": "757297f1-9325-4df4-af51-96510be76bf3",
      "Name": "Expanded Polystyrene (EPS) Foam Insulation (density 20 kg/m³)",
      "Conformity": "'DIN EN 15804+A2' / 'ISO 14025'",
      "Laenderkennung": "DE",
      "Declaration owner": "Bundesfachabteilung Qualitätssicherung EPS-Hartschaum BFA QS EPS",
      "Registrierungsnummer": "EPD-IVH-20220130-CBG1-DE",
      "Bezugsgroesse": "1",
      "Reference": "m3",
      "Density (kg/m3)": "20.0",
      "GWPtotal (A1-A3)": "59.806",
      "GWPtotal (A5)": "0.39",
      "GWPtotal (C1)": "0.0",
      "GWPtotal (C2)": "0.0604",
      "GWPtotal (C3)": "67.2",
      "GWPtotal (C4)": "0.0",
      "GWPbiogenic": "0.320681",
      "GWPfossil": "127.1928",
      "GWPtotal": "127.4564"
    },
    {
      "ID": "cb582d00-b984-4bb8-ab2e-5302678a721d",
      "Name": "Expanded Polystyrene (EPS) Foam Insulation (density 25 kg/m³)",
      "Conformity": "'DIN EN 15804+A2' / 'ISO 14025'",
      "Laenderkennung": "DE",
      "Declaration owner": "Industrieverband Hartschaum e.V., IVH",
      "Registrierungsnummer": "EPD-IVH-20220131-CBG1-DE",
      "Bezugsgroesse": "1",
      "Reference": "m3",
      "Density (kg/m3)": "25.0",
      "GWPtotal (A1-A3)": "77.448",
      "GWPtotal (A5)": "0.501",
      "GWPtotal (C1)": "0.0",
      "GWPtotal (C2)": "0.0756",
      "GWPtotal (C3)": "84.0",
      "GWPtotal (C4)": "0.0",
      "GWPbiogenic": "0.381473",
      "GWPfossil": "161.5838",
      "GWPtotal": "162.0246"
    },
    {
      "ID": "4e83c488-bb36-40b0-bfd4-b2aa7f1c0f04",
      "Name": "Expanded Polystyrene (EPS) Foam Insulation (density 30 kg/m³)",
      "Conformity": "'DIN EN 15804+A2' / 'ISO 14025'",
      "Laenderkennung": "DE",
      "Declaration owner": "Industrieverband Hartschaum e.V., IVH",
      "Registrierungsnummer": "EPD-IVH-20220132-CBG1-DE",
      "Bezugsgroesse": "1",
      "Reference": "m3",
      "Density (kg/m3)": "30.0",
      "GWPtotal (A1-A3)": "87.74",
      "GWPtotal (A5)": "0.571",
      "GWPtotal (C1)": "0.0",
      "GWPtotal (C2)": "0.0907",
      "GWPtotal (C3)": "101.0",
      "GWPtotal (C4)": "0.0",
      "GWPbiogenic": "0.489357",
      "GWPfossil": "188.9088",
      "GWPtotal": "189.4017"
    },
    {
      "ID": "8f6daa87-b2ee-4eb0-95e0-737ac8c6a59f",
      "Name": "Polystyrene foam filling (cement bound)",
      "Conformity": "'EN 15804+A2 (EF 3.1)'",
      "Laenderkennung": "DE",
      "Declaration owner": "Sphera Solutions GmbH",
      "Bezugsgroesse": "1",
      "Reference": "m3",
      "Density (kg/m3)": "350.0",
      "GWPtotal (A1-A3)": "168.5521331",
      "GWPtotal (C2)": "0.1192825",
      "GWPtotal (C3)": "103.3604836",
      "GWPbiogenic": "0.6520912",
      "GWPfossil": "271.3304149",
      "GWPtotal": "272.0318993"
    },
    {
      "ID": "f2552bdf-c847-4ef8-9665-c37e8ef4d44d",
      "Name": "Polystyrene foam filling (without binder)",
      "Conformity": "'EN 15804+A2 (EF 3.1)'",
      "Laenderkennung": "DE",
      "Declaration owner": "Sphera Solutions GmbH",
      "Bezugsgroesse": "1",
      "Reference": "m3",
      "Density (kg/m3)": "15.0",
      "GWPtotal (A1-A3)": "52.7329154",
      "GWPtotal (C2)": "0.0639014",
      "GWPtotal (C3)": "55.3716877",
      "GWPbiogenic": "0.3059104",
      "GWPfossil": "107.8492233",
      "GWPtotal": "108.1685044"
    }
  ]
}