{
  "type": "materials",
  "path": "Komponenten von Fenstern und Vorhangfassaden / Beschläge / Befestigungen",
  "items": [
    {
      "ID": "bbb0e5c6-d9f2-4ad3-a633-671f67e7f91b",
      "Name": "8600 and 8900 Series door closers",
      "Conformity": "'DIN EN 15804' / 'ISO 14025'",
      "Laenderkennung": "DE",
      "Declaration owner": "dormakaba International Holding GmbH",
      "Registrierungsnummer": "EPD-DOR-20200384-CBD3-EN",
      "Bezugsgroesse": "1",
      "Reference": "pcs.",
      "Stueckgewicht (kg)": "3.0",
      "GWPbiogenic": "0.0",
      "GWPfossil": "0.0",
      "GWPtotal": "0.0"
    },
    {
      "ID": "454898b5-c2d1-48a5-a812-b5e54dd859f0",
      "Name": "BEST 1C Series",
      "Conformity": "'DIN EN 15804+A2' / 'ISO 14025'",
      "Laenderkennung": "US",
      "Declaration owner": "dormakaba International Holding GmbH",
      "Registrierungsnummer": "EPD-DOR-20210304-CBA8-EN",
      "Bezugsgroesse": "1",
      "Reference": "pcs.",
      "Stueckgewicht (kg)": "0.0449",
      "GWPtotal (A1-A3)": "0.31",
      "GWPtotal (A4)": "0.007",
      "GWPtotal (A5)": "0.002",
      "GWPtotal (C1)": "0.0",
      "GWPtotal (C2)": "0.0001915",
      "GWPtotal (C3)": "0.0",
      "GWPtotal (C4)": "0.0",
      "GWPbiogenic": "0.0113197",
      "GWPfossil": "0.3072222",
      "GWPtotal": "0.3191915"
    },
    {
      "ID": "d6c4305f-5ae1-45a9-926b-43de195e34a4",
      "Name": "BEST 1E Series",
      "Conformity": "'DIN EN 15804+A2' / 'ISO 14025'",
      "Laenderkennung": "RNA",
      "Declaration owner": "dormakaba International Holding GmbH",
      "Registrierungsnummer": "EPD-DOR-20210303-CBA1-EN",
      "Bezugsgroesse": "1",
      "Reference": "pcs.",
      "Stueckgewicht (kg)": "0.26",
      "GWPtotal (A1-A3)": "10.6",
      "GWPtotal (A4)": "0.0367",
      "GWPtotal (A5)": "0.316",
      "GWPtotal (C1)": "0.0",
      "GWPtotal (C2)": "0.0174",
      "GWPtotal (C3)": "0.569",
      "GWPtotal (C4)": "0.00493",
      "GWPbiogenic": "-0.077582",
      "GWPfossil": "11.6385",
      "GWPtotal": "11.54403"
    },
    {
      "ID": "dd902c86-84dd-47b8-a45a-bab0b054bc72",
      "Name": "BEST 45H Mortise Series",
      "Conformity": "'DIN EN 15804+A2' / 'ISO 14025'",
      "Laenderkennung": "US",
      "Declaration owner": "dormakaba International Holding GmbH",
      "Registrierungsnummer": "EPD-DOR-20210335-CBA6-EN",
      "Bezugsgroesse": "1",
      "Reference": "pcs.",
      "Stueckgewicht (kg)": "3.8",
      "GWPtotal (A1-A3)": "9.938",
      "GWPtotal (A4)": "0.623",
      "GWPtotal (A5)": "0.000241",
      "GWPtotal (B6)": "0.0",
      "GWPtotal (C1)": "0.0",
      "GWPtotal (C2)": "0.017",
      "GWPtotal (C3)": "0.063",
      "GWPtotal (C4)": "0.003",
      "GWPbiogenic": "0.0759786",
      "GWPfossil": "10.557006",
      "GWPtotal": "10.644241"
    },
    {
      "ID": "5db4f6bd-ea87-400b-b4ac-6a51388fa9d4",
      "Name": "BEST 47H Mortise Series",
      "Conformity": "'DIN EN 15804+A2' / 'ISO 14025'",
      "Laenderkennung": "US",
      "Declaration owner": "dormakaba International Holding GmbH",
      "Registrierungsnummer": "EPD-DOR-20220212-CBA1-EN",
      "Bezugsgroesse": "1",
      "Reference": "pcs.",
      "Stueckgewicht (kg)": "3.8",
      "GWPtotal (A1-A3)": "9.938",
      "GWPtotal (A4)": "0.623",
      "GWPtotal (A5)": "0.000241",
      "GWPtotal (C1)": "0.0",
      "GWPtotal (C2)": "0.017",
      "GWPtotal (C3)": "0.063",
      "GWPtotal (C4)": "0.003",
      "GWPbiogenic": "0.0759786",
      "GWPfossil": "10.557006",
      "GWPtotal": "10.644241"
    },
    {
      "ID": "06f97760-c2e3-4d01-9ea8-1c72def5df66",
      "Name": "BEST 9K Cylindrical Series",
      "Conformity": "'DIN EN 15804+A2' / 'ISO 14025'",
      "Laenderkennung": "US",
      "Declaration owner": "dormakaba International Holding GmbH",
      "Registrierungsnummer": "EPD-DOR-20210340-CBA7-EN",
      "Bezugsgroesse": "1",
      "Reference": "pcs.",
      "Stueckgewicht (kg)": "2.08",
      "GWPtotal (A1-A3)": "5.741",
      "GWPtotal (A4)": "0.341",
      "GWPtotal (A5)": "0.252",
      "GWPtotal (B6)": "123.0",
      "GWPtotal (C1)": "0.0",
      "GWPtotal (C2)": "0.008",
      "GWPtotal (C3)": "0.008",
      "GWPtotal (C4)": "0.002",
      "GWPbiogenic": "0.0137766",
      "GWPfossil": "129.3",
      "GWPtotal": "129.352"
    },
    {
      "ID": "6557908e-d613-452b-812f-c72c4363c83d",
      "Name": "BEST T Deadbolt Series",
      "Conformity": "'DIN EN 15804+A2' / 'ISO 14025'",
      "Laenderkennung": "RNA",
      "Declaration owner": "dormakaba International Holding GmbH",
      "Registrierungsnummer": "EPD-DOR-20210320-CBA1-EN",
      "Bezugsgroesse": "1",
      "Reference": "pcs.",
      "Stueckgewicht (kg)": "1.26",
      "GWPtotal (A1-A3)": "2.489",
      "GWPtotal (A4)": "0.205",
      "GWPtotal (A5)": "0.274",
      "GWPtotal (B6)": "0.0",
      "GWPtotal (C1)": "0.0",
      "GWPtotal (C2)": "0.005",
      "GWPtotal (C3)": "0.017",
      "GWPtotal (C4)": "3.1e-06",
      "GWPbiogenic": "0.0192285",
      "GWPfossil": "2.968003",
      "GWPtotal": "2.9900031"
    },
    {
      "ID": "3fa36a6b-6dce-428e-b622-9a7521ee97ea",
      "Name": "Fastening solutions for external thermal insulation composite systems",
      "Conformity": "'DIN EN 15804+A2' / 'ISO 14025'",
      "Laenderkennung": "RER",
      "Declaration owner": "EJOT BAUBEFESTIGUNGEN GmbH",
      "Registrierungsnummer": "EPD-EJO-20210060-IBD1-DE",
      "Bezugsgroesse": "not available",
      "GWPtotal (A1-A3)": "0.811",
      "GWPtotal (C1)": "0.00257",
      "GWPtotal (C2)": "0.00126",
      "GWPtotal (C3)": "0.000526",
      "GWPtotal (C4)": "0.00437",
      "GWPbiogenic": "-4e-07",
      "GWPfossil": "0.819682",
      "GWPtotal": "0.819726"
    },
    {
      "ID": "25295071-852e-4b85-be91-f9901c0a4f7b",
      "Name": "Fastening systems for rear-ventilated curtain wall facades",
      "Conformity": "'DIN EN 15804+A2' / 'ISO 14025'",
      "Laenderkennung": "RER",
      "Declaration owner": "EJOT BAUBEFESTIGUNGEN GmbH",
      "Registrierungsnummer": "EPD-EJO-20210061-IBD1-DE",
      "Bezugsgroesse": "not available",
      "GWPtotal (A1-A3)": "0.671",
      "GWPtotal (C1)": "0.00256",
      "GWPtotal (C2)": "0.000895",
      "GWPtotal (C3)": "0.000341",
      "GWPtotal (C4)": "0.00221",
      "GWPbiogenic": "0.0",
      "GWPfossil": "0.675976",
      "GWPtotal": "0.677006"
    },
    {
      "ID": "3a29b318-f4cb-411b-b13e-8565adae20e7",
      "Name": "Flat roof fastening systems",
      "Conformity": "'DIN EN 15804+A2' / 'ISO 14025'",
      "Laenderkennung": "RER",
      "Declaration owner": "EJOT BAUBEFESTIGUNGEN GmbH",
      "Registrierungsnummer": "EPD-EJO-20210059-IBD1-DE",
      "Bezugsgroesse": "not available",
      "GWPtotal (A1-A3)": "0.491",
      "GWPtotal (C1)": "0.00256",
      "GWPtotal (C2)": "0.000658",
      "GWPtotal (C3)": "0.000255",
      "GWPtotal (C4)": "0.00174",
      "GWPbiogenic": "0.0",
      "GWPfossil": "0.496186",
      "GWPtotal": "0.496213"
    },
    {
      "ID": "889e2819-01be-4aa4-b7d3-d19e01e75c02",
      "Name": "Galvanized steel screws",
      "Conformity": "'EN 15804+A2 (EF 3.1)'",
      "Laenderkennung": "DE",
      "Declaration owner": "Sphera Solutions GmbH",
      "Bezugsgroesse": "1",
      "Reference": "kg",
      "GWPtotal (A1-A3)": "3.461258",
      "GWPtotal (C1)": "0.0003294",
      "GWPtotal (C2)": "0.0046454",
      "GWPtotal (C3)": "0.0",
      "GWPbiogenic": "0.0076394",
      "GWPfossil": "3.4571653",
      "GWPtotal": "3.4662328"
    },
    {
      "ID": "5d28c3d4-4553-4608-966a-c4ccadf8d260",
      "Name": "ITS 915/ITS 900",
      "Conformity": "'DIN EN 15804+A2' / 'ISO 14025'",
      "Laenderkennung": "SG",
      "Declaration owner": "dormakaba International Holding GmbH",
      "Registrierungsnummer": "EPD-DOR-20220160-CBA1-EN",
      "Bezugsgroesse": "1",
      "Reference": "pcs.",
      "Stueckgewicht (kg)": "1.98",
      "GWPtotal (A1-A3)": "10.332",
      "GWPtotal (A4)": "0.723",
      "GWPtotal (A5)": "0.268",
      "GWPtotal (C1)": "0.0",
      "GWPtotal (C2)": "0.008",
      "GWPtotal (C3)": "0.044",
      "GWPtotal (C4)": "0.002",
      "GWPbiogenic": "-0.0157734",
      "GWPfossil": "11.388",
      "GWPtotal": "11.377"
    },
    {
      "ID": "c75af9d3-f5f1-4712-a82c-d66bf8282969",
      "Name": "LA GARD 700",
      "Conformity": "'DIN EN 15804+A2' / 'ISO 14025'",
      "Laenderkennung": "MX",
      "Declaration owner": "dormakaba International Holding GmbH",
      "Registrierungsnummer": "EPD-DOR-20210247-CBA3-EN",
      "Bezugsgroesse": "1",
      "Reference": "pcs.",
      "Stueckgewicht (kg)": "0.606",
      "GWPtotal (A1-A3)": "15.1424",
      "GWPtotal (A4)": "1.06",
      "GWPtotal (A5)": "0.0179",
      "GWPtotal (B2)": "0.3",
      "GWPtotal (B6)": "0.0153",
      "GWPtotal (C1)": "0.0",
      "GWPtotal (C2)": "0.00265",
      "GWPtotal (C3)": "0.251",
      "GWPtotal (C4)": "0.0003",
      "GWPbiogenic": "0.0410742",
      "GWPfossil": "16.701675",
      "GWPtotal": "16.78955"
    },
    {
      "ID": "86610a38-3ad1-44a6-8aa4-f8c49bbca136",
      "Name": "Ladder Pull TG138 Series",
      "Conformity": "'DIN EN 15804+A2' / 'ISO 14025'",
      "Laenderkennung": "RNA",
      "Declaration owner": "dormakaba International Holding GmbH",
      "Registrierungsnummer": "EPD-DOR-20210203-CBC1-EN",
      "Bezugsgroesse": "1",
      "Reference": "pcs.",
      "Stueckgewicht (kg)": "6.97",
      "GWPtotal (A1-A3)": "42.2167",
      "GWPtotal (A4)": "0.0653",
      "GWPtotal (A5)": "0.813",
      "GWPtotal (C1)": "0.0",
      "GWPtotal (C2)": "0.0309",
      "GWPtotal (C3)": "0.0229",
      "GWPtotal (C4)": "0.00153",
      "GWPbiogenic": "0.0111957",
      "GWPfossil": "42.98522",
      "GWPtotal": "43.15033"
    },
    {
      "ID": "fd98c183-4cce-4765-8490-f63e13a7bb38",
      "Name": "Precision 2000 Series",
      "Conformity": "'DIN EN 15804+A2' / 'ISO 14025'",
      "Laenderkennung": "US",
      "Declaration owner": "dormakaba International Holding GmbH",
      "Registrierungsnummer": "EPD-DOR-20220039-CBA1-EN",
      "Bezugsgroesse": "1",
      "Reference": "pcs.",
      "Stueckgewicht (kg)": "12.04",
      "GWPtotal (A1-A3)": "51.496",
      "GWPtotal (A4)": "1.973",
      "GWPtotal (A5)": "0.989",
      "GWPtotal (B6)": "175.28",
      "GWPtotal (C1)": "0.0",
      "GWPtotal (C2)": "0.049",
      "GWPtotal (C3)": "0.032",
      "GWPtotal (C4)": "0.009",
      "GWPbiogenic": "0.0410323",
      "GWPfossil": "229.659",
      "GWPtotal": "229.828"
    },
    {
      "ID": "98458824-c819-4a31-bf1f-7dec368bba0d",
      "Name": "Remote reader 91 15",
      "Conformity": "'DIN EN 15804+A2' / 'ISO 14025'",
      "Laenderkennung": "DE",
      "Declaration owner": "dormakaba International Holding GmbH",
      "Registrierungsnummer": "EPD-DOR-20220214-CBA2-EN",
      "Bezugsgroesse": "1",
      "Reference": "pcs.",
      "Stueckgewicht (kg)": "0.185",
      "GWPtotal (A1-A3)": "0.124",
      "GWPtotal (A4)": "0.002",
      "GWPtotal (A5)": "0.076",
      "GWPtotal (B6)": "68.74",
      "GWPtotal (C1)": "0.0",
      "GWPtotal (C2)": "0.0002451",
      "GWPtotal (C3)": "0.109",
      "GWPtotal (C4)": "0.0001908",
      "GWPbiogenic": "0.1823688",
      "GWPfossil": "68.7744239",
      "GWPtotal": "69.0514359"
    },
    {
      "ID": "e044e63f-b7dd-4dd0-9c20-5ada97f5398a",
      "Name": "Remote reader 91 25",
      "Conformity": "'DIN EN 15804+A2' / 'ISO 14025'",
      "Laenderkennung": "DE",
      "Declaration owner": "dormakaba International Holding GmbH",
      "Registrierungsnummer": "EPD-DOR-20220258-CBA2-EN",
      "Bezugsgroesse": "1",
      "Reference": "pcs.",
      "Stueckgewicht (kg)": "0.249",
      "GWPtotal (A1-A3)": "4.175",
      "GWPtotal (A4)": "0.002",
      "GWPtotal (A5)": "0.102",
      "GWPtotal (B6)": "99.599",
      "GWPtotal (C1)": "0.0",
      "GWPtotal (C2)": "0.0006205",
      "GWPtotal (C3)": "0.163",
      "GWPtotal (C4)": "7.6e-06",
      "GWPbiogenic": "0.110522",
      "GWPfossil": "103.7896007",
      "GWPtotal": "104.0416281"
    },
    {
      "ID": "2cfd1b93-cb47-4ccd-934c-eee45283a12d",
      "Name": "Reversible Single Cylinder - ace JP, ace APAC",
      "Conformity": "'DIN EN 15804+A2' / 'ISO 14025'",
      "Laenderkennung": "CN",
      "Declaration owner": "dormakaba International Holding GmbH",
      "Registrierungsnummer": "EPD-DOR-20210232-CBC1-EN",
      "Bezugsgroesse": "1",
      "Reference": "pcs.",
      "Stueckgewicht (kg)": "3.58",
      "GWPtotal (A1-A3)": "1.159",
      "GWPtotal (A4)": "0.06",
      "GWPtotal (A5)": "0.042",
      "GWPtotal (C1)": "0.0",
      "GWPtotal (C2)": "0.001",
      "GWPtotal (C3)": "0.011",
      "GWPtotal (C4)": "0.0",
      "GWPbiogenic": "-0.0004555",
      "GWPfossil": "1.272",
      "GWPtotal": "1.273"
    },
    {
      "ID": "6c46fc8d-6a74-415b-8e6b-b90af72178ac",
      "Name": "Stainless steel screws",
      "Conformity": "'EN 15804+A2 (EF 3.1)'",
      "Laenderkennung": "DE",
      "Declaration owner": "Sphera Solutions GmbH",
      "Bezugsgroesse": "1",
      "Reference": "kg",
      "Density (kg/m3)": "7850.0",
      "GWPtotal (A1-A3)": "4.1834809",
      "GWPtotal (C1)": "0.0",
      "GWPtotal (C2)": "0.003714",
      "GWPbiogenic": "0.0025907",
      "GWPfossil": "4.1805762",
      "GWPtotal": "4.1871949"
    },
    {
      "ID": "ac1792fd-68bb-4344-b9d8-dd33b7e48be0",
      "Name": "TS 68/TS 69",
      "Conformity": "'DIN EN 15804+A2' / 'ISO 14025'",
      "Laenderkennung": "CN",
      "Declaration owner": "dormakaba International Holding GmbH",
      "Registrierungsnummer": "EPD-DOR-20220088-CBA8-EN",
      "Bezugsgroesse": "1",
      "Reference": "pcs.",
      "Stueckgewicht (kg)": "2.07",
      "GWPtotal (A1-A3)": "14.57",
      "GWPtotal (A4)": "0.339",
      "GWPtotal (A5)": "0.193",
      "GWPtotal (C1)": "0.0",
      "GWPtotal (C2)": "0.008",
      "GWPtotal (C3)": "0.246",
      "GWPtotal (C4)": "0.001",
      "GWPbiogenic": "-0.0086184",
      "GWPfossil": "15.358",
      "GWPtotal": "15.357"
    },
    {
      "ID": "59ff4420-4b5d-451e-a349-ebf08b2c5cc8",
      "Name": "TS 71/TS 72",
      "Conformity": "'DIN EN 15804+A2' / 'ISO 14025'",
      "Laenderkennung": "CN",
      "Declaration owner": "dormakaba International Holding GmbH",
      "Registrierungsnummer": "EPD-DOR-20220164-CBA1-EN",
      "Bezugsgroesse": "1",
      "Reference": "pcs.",
      "Stueckgewicht (kg)": "1.74",
      "GWPtotal (A1-A3)": "13.044",
      "GWPtotal (A4)": "0.133",
      "GWPtotal (A5)": "0.157",
      "GWPtotal (C1)": "0.0",
      "GWPtotal (C2)": "0.007",
      "GWPtotal (C3)": "0.415",
      "GWPtotal (C4)": "0.0",
      "GWPbiogenic": "-0.0066854",
      "GWPfossil": "13.755",
      "GWPtotal": "13.756"
    },
    {
      "ID": "1cf38ce1-36f6-4819-9ba7-e39235c41bc9",
      "Name": "TS 73 V",
      "Conformity": "'DIN EN 15804+A2' / 'ISO 14025'",
      "Laenderkennung": "SG",
      "Declaration owner": "dormakaba International Holding GmbH",
      "Registrierungsnummer": "EPD-DOR-20220161-CBA1-EN",
      "Bezugsgroesse": "1",
      "Reference": "pcs.",
      "Stueckgewicht (kg)": "2.11",
      "GWPtotal (A1-A3)": "20.225",
      "GWPtotal (A4)": "0.838",
      "GWPtotal (A5)": "0.122",
      "GWPtotal (C1)": "0.0",
      "GWPtotal (C2)": "0.009",
      "GWPtotal (C3)": "0.043",
      "GWPtotal (C4)": "0.002",
      "GWPbiogenic": "-0.0136028",
      "GWPfossil": "21.247",
      "GWPtotal": "21.239"
    },
    {
      "ID": "44a07da3-eae8-4d97-9909-747d635fb07e",
      "Name": "TS 83",
      "Conformity": "'DIN EN 15804+A2' / 'ISO 14025'",
      "Laenderkennung": "SG",
      "Declaration owner": "dormakaba International Holding GmbH",
      "Registrierungsnummer": "EPD-DOR-20220163-CBA1-EN",
      "Bezugsgroesse": "1",
      "Reference": "pcs.",
      "Stueckgewicht (kg)": "2.65",
      "GWPtotal (A1-A3)": "23.042",
      "GWPtotal (A4)": "0.979",
      "GWPtotal (A5)": "0.122",
      "GWPtotal (C1)": "0.0",
      "GWPtotal (C2)": "0.011",
      "GWPtotal (C3)": "0.463",
      "GWPtotal (C4)": "0.0",
      "GWPbiogenic": "0.0174781",
      "GWPfossil": "24.594",
      "GWPtotal": "24.617"
    },
    {
      "ID": "cdf23e80-b2db-40ea-985b-058ab5f3f681",
      "Name": "TS 90 Impulse",
      "Conformity": "'DIN EN 15804+A2' / 'ISO 14025'",
      "Laenderkennung": "SG",
      "Declaration owner": "dormakaba International Holding GmbH",
      "Registrierungsnummer": "EPD-DOR-20220068-CBA7-EN",
      "Bezugsgroesse": "1",
      "Reference": "pcs.",
      "Stueckgewicht (kg)": "2.5",
      "GWPtotal (A1-A3)": "7.496",
      "GWPtotal (A4)": "0.305",
      "GWPtotal (A5)": "0.825",
      "GWPtotal (C1)": "0.0",
      "GWPtotal (C2)": "0.008",
      "GWPtotal (C3)": "0.048",
      "GWPtotal (C4)": "0.002",
      "GWPbiogenic": "-0.1186286",
      "GWPfossil": "8.797",
      "GWPtotal": "8.684"
    },
    {
      "ID": "7c9336b4-4792-4a21-8fe6-12233b9e32d1",
      "Name": "TS 91",
      "Conformity": "'DIN EN 15804+A2' / 'ISO 14025'",
      "Laenderkennung": "SG",
      "Declaration owner": "dormakaba International Holding GmbH",
      "Registrierungsnummer": "EPD-DOR-20220162-CBA1-EN",
      "Bezugsgroesse": "1",
      "Reference": "pcs.",
      "Stueckgewicht (kg)": "2.75",
      "GWPtotal (A1-A3)": "19.332",
      "GWPtotal (A4)": "0.21",
      "GWPtotal (A5)": "0.366",
      "GWPtotal (C1)": "0.0",
      "GWPtotal (C2)": "0.011",
      "GWPtotal (C3)": "0.106",
      "GWPtotal (C4)": "0.002",
      "GWPbiogenic": "-0.0755084",
      "GWPfossil": "20.095",
      "GWPtotal": "20.027"
    },
    {
      "ID": "2d429f70-485b-47d5-a1f7-351d52325c46",
      "Name": "TS 92 XEA",
      "Conformity": "'DIN EN 15804+A2' / 'ISO 14025'",
      "Laenderkennung": "SG",
      "Declaration owner": "dormakaba International Holding GmbH",
      "Registrierungsnummer": "EPD-DOR-20220215-CBA1-EN",
      "Bezugsgroesse": "1",
      "Reference": "pcs.",
      "Stueckgewicht (kg)": "3.34",
      "GWPtotal (A1-A3)": "25.153",
      "GWPtotal (A4)": "0.237",
      "GWPtotal (A5)": "0.085",
      "GWPtotal (C1)": "0.0",
      "GWPtotal (C2)": "0.014",
      "GWPtotal (C3)": "1.293",
      "GWPtotal (C4)": "0.0",
      "GWPbiogenic": "0.0759035",
      "GWPfossil": "26.699",
      "GWPtotal": "26.782"
    },
    {
      "ID": "268bc86a-2d3b-41b7-bc46-b552e51722d9",
      "Name": "Terminal 96 00",
      "Conformity": "'DIN EN 15804+A2' / 'ISO 14025'",
      "Laenderkennung": "DE",
      "Declaration owner": "dormakaba International Holding GmbH",
      "Registrierungsnummer": "EPD-DOR-20210209-CBA2-EN",
      "Bezugsgroesse": "1",
      "Reference": "pcs.",
      "Umrechungsfaktor auf 1kg": "1.32",
      "GWPtotal (A1-A3)": "47.586",
      "GWPtotal (A4)": "0.102",
      "GWPtotal (A5)": "3.17",
      "GWPtotal (B6)": "328.0",
      "GWPtotal (C1)": "0.0",
      "GWPtotal (C2)": "0.0383",
      "GWPtotal (C3)": "0.144",
      "GWPtotal (C4)": "0.028",
      "GWPbiogenic": "1.4121286",
      "GWPfossil": "376.6651",
      "GWPtotal": "379.0683"
    },
    {
      "ID": "c7136b6b-c9cc-4f74-bb5a-575bb9edacc3",
      "Name": "Terminal 97 00",
      "Conformity": "'DIN EN 15804+A2' / 'ISO 14025'",
      "Laenderkennung": "DE",
      "Declaration owner": "dormakaba International Holding GmbH",
      "Registrierungsnummer": "EPD-DOR-20210284-CBA1-EN",
      "Bezugsgroesse": "1",
      "Reference": "pcs.",
      "Stueckgewicht (kg)": "0.476",
      "GWPtotal (A1-A3)": "60.246",
      "GWPtotal (A4)": "0.332",
      "GWPtotal (A5)": "0.851",
      "GWPtotal (B6)": "198.0",
      "GWPtotal (C1)": "0.0",
      "GWPtotal (C2)": "0.007",
      "GWPtotal (C3)": "1.419",
      "GWPtotal (C4)": "0.009",
      "GWPbiogenic": "1.1303561",
      "GWPfossil": "487.661",
      "GWPtotal": "260.864"
    },
    {
      "ID": "f1752f63-92a0-4f29-aa68-2e57c26b9eaf",
      "Name": "c-lever compact",
      "Conformity": "'DIN EN 15804+A2' / 'ISO 14025'",
      "Laenderkennung": "CN",
      "Declaration owner": "dormakaba International Holding GmbH",
      "Registrierungsnummer": "EPD-DOR-20210339-CBA2-EN",
      "Bezugsgroesse": "1",
      "Reference": "pcs.",
      "Stueckgewicht (kg)": "1.28",
      "GWPtotal (A1-A3)": "12.37",
      "GWPtotal (A4)": "0.197",
      "GWPtotal (A5)": "0.473",
      "GWPtotal (B6)": "0.011",
      "GWPtotal (C1)": "0.0",
      "GWPtotal (C2)": "0.004",
      "GWPtotal (C3)": "0.138",
      "GWPtotal (C4)": "0.0004843",
      "GWPbiogenic": "0.130222",
      "GWPfossil": "13.0554813",
      "GWPtotal": "13.1934843"
    }
  ]
}